groom/__init__.py
groom/__main__.py
groom/annotations.py
groom/dispatching.py
groom-0.1.0b1.dist-info/LICENSE
groom-0.1.0b1.dist-info/METADATA
groom-0.1.0b1.dist-info/WHEEL
groom-0.1.0b1.dist-info/top_level.txt
groom-0.1.0b1.dist-info/RECORD
