Metadata-Version: 2.1
Name: groom
Version: 0.1.0b1
Summary: A easy-to-use command-line interface generator
Home-page: https://github.com/frodo821/groom
Author: frodo821 <Twitter: @BoufrawFrodo2>
Author-email: 1234567890.sakai.jp@gmail.com
Maintainer: frodo821 <Twitter: @BoufrawFrodo2>
Maintainer-email: 1234567890.sakai.jp@gmail.com
License: MIT
Platform: UNKNOWN
Classifier: Programming Language :: Python :: 3
Classifier: Programming Language :: Python :: 3.6
Classifier: Programming Language :: Python :: 3.7
Classifier: Programming Language :: Python :: 3.8
Classifier: License :: OSI Approved :: MIT License
Classifier: Development Status :: 3 - Alpha
Classifier: Intended Audience :: Developers
Classifier: Operating System :: OS Independent
Classifier: Topic :: Utilities
Classifier: Topic :: Terminals
Classifier: Topic :: Software Development :: Libraries :: Application Frameworks
